koltk/__init__.py
koltk/corpus/__init__.py
koltk/corpus/nikl/__init__.py
koltk/corpus/nikl/annotated/__init__.py
koltk/corpus/nikl/annotated/base.py
koltk/corpus/nikl/annotated/encoder.py
koltk/corpus/nikl/annotated/object.py
koltk/corpus/nikl/annotated/reader.py
koltk/corpus/nikl/annotated/tag.py
koltk/corpus/nikl/json/__init__.py
koltk/corpus/nikl/json/base.py
koltk/corpus/nikl/json/encoder.py
koltk/corpus/nikl/json/object.py
koltk/corpus/sejong/Allomorph.py
koltk/corpus/sejong/__init__.py
koltk/corpus/sejong/dep.py
koltk/corpus/sejong/morph.py
koltk/corpus/sejong/parsed.py
koltk/corpus/sejong/sense.py
koltk-0.1.0.dist-info/LICENSE
koltk-0.1.0.dist-info/METADATA
koltk-0.1.0.dist-info/WHEEL
koltk-0.1.0.dist-info/top_level.txt
koltk-0.1.0.dist-info/RECORD
