Metadata-Version: 2.1
Name: koltk
Version: 0.1.0
Summary: Korean Language Toolkit
Home-page: https://github.com/koltk/koltk
Author: youhyunjo
Author-email: you@cpan.org
License: UNKNOWN
Platform: UNKNOWN
Classifier: Programming Language :: Python :: 3
Classifier: License :: OSI Approved :: GNU General Public License v3 or later (GPLv3+)
Classifier: Operating System :: OS Independent
Requires-Python: >=3.8
License-File: LICENSE
